seyuri_utils/Logger.py
seyuri_utils/Timer.py
seyuri_utils/__init__.py
seyuri_utils/utils.py
Seyuri_Utils-1.0.dist-info/METADATA
Seyuri_Utils-1.0.dist-info/WHEEL
Seyuri_Utils-1.0.dist-info/top_level.txt
Seyuri_Utils-1.0.dist-info/RECORD
