Metadata-Version: 2.1
Name: Seyuri-Utils
Version: 1.0
Summary: This package contains some useful functions
Requires-Dist: colorama
